libtemplate/__init__.py
libtemplate/__main__.py
libtemplate/_version.py
libtemplate/cli.py
libtemplate-0.0.2.dist-info/AUTHORS.rst
libtemplate-0.0.2.dist-info/METADATA
libtemplate-0.0.2.dist-info/WHEEL
libtemplate-0.0.2.dist-info/entry_points.txt
libtemplate-0.0.2.dist-info/top_level.txt
libtemplate-0.0.2.dist-info/RECORD
