Metadata-Version: 2.1
Name: libtemplate
Version: 0.0.2
Summary: Template for python packages generated with cookiecutter-pylibrary
Home-page: https://github.com/jpardovega/libtemplate
Author: Javier Pardo Vega
Author-email: eljavico@gmail.com
License: UNKNOWN
Project-URL: Documentation, https://libtemplate.readthedocs.io/
Project-URL: Changelog, https://libtemplate.readthedocs.io/en/latest/changelog.html
Project-URL: Issue Tracker, https://github.com/jpardovega/libtemplate/issues
Platform: UNKNOWN
Classifier: Development Status :: 5 - Production/Stable
Classifier: Intended Audience :: Developers
Classifier: Operating System :: Unix
Classifier: Operating System :: POSIX
Classifier: Operating System :: Microsoft :: Windows
Classifier: Programming Language :: Python
Classifier: Programming Language :: Python :: 3
Classifier: Programming Language :: Python :: 3 :: Only
Classifier: Programming Language :: Python :: 3.6
Classifier: Programming Language :: Python :: 3.7
Classifier: Programming Language :: Python :: 3.8
Classifier: Programming Language :: Python :: 3.9
Classifier: Programming Language :: Python :: Implementation :: CPython
Classifier: Programming Language :: Python :: Implementation :: PyPy
Classifier: Topic :: Utilities
Requires-Python: >=3.6
Requires-Dist: pandas
Requires-Dist: numpy
